[
  {
    "fecha": "1980",
    "titulo": "lorem ipsum dolor sit",
    "descripcion": "Lorem ipsum dolor sit amet consectetur. Mollis in in blandit mattis. Rhoncus quam tempus cras"
  },
  {
    "fecha": "1980",
    "titulo": "lorem ipsum dolor sit",
    "descripcion": "Lorem ipsum dolor sit amet consectetur. Mollis in in blandit mattis. Rhoncus quam tempus cras"
  },
  {
    "fecha": "1980",
    "titulo": "lorem ipsum dolor sit",
    "descripcion": "Lorem ipsum dolor sit amet consectetur. Mollis in in blandit mattis. Rhoncus quam tempus cras"
  },
  {
    "fecha": "1980",
    "titulo": "lorem ipsum dolor sit",
    "descripcion": "Lorem ipsum dolor sit amet consectetur. Mollis in in blandit mattis. Rhoncus quam tempus cras"
  }
]
